{
    "translation":{
        "INSCREVA-SE HOJE MESMO":"SIGN UP TODAY",
        "Participe do primeiro evento online unindo portugueses e brasileiros para apresentar e debater Customer Experience e Customer Success.":"Participate in the first online event uniting Portuguese and Brazilians to present and discuss Customer Experience and Customer Success.",
        "Quero me inscrever agora":"I want to register now",
        "QUERO SER PATROCINADOR":"I WANT TO BE A SPONSOR",
        "BENEFÍCIOS EM PARTICIPAR":"BENEFITS OF PARTICIPATING",
        "Apresentação de casos de sucesso de empresas que implantaram CX e CS com grandes resultados.":"Presentation of successful cases of companies that implemented CX and CS with great results.",
        "Debates sobre tendências internacionais para ampliar seus conhecimentos em CX e CS.":"Debates on international trends to broaden your knowledge in CX and CS.",
        "Networking direcionado com referências em CX e CS em seus países.":"Targeted networking with CX and CS references in their countries.",
        "Soluções para aumentar os resultados da sua empresa e dos seus clientes.":"Solutions to increase the results of your company and your customers.",
        "Oportunidade de aprofundar o entendimento sobre CX e CS e a complementaridades entre eles.":"Opportunity to deepen understanding of CX and CS and the complementarities between them.",
        "CONTAGEM REGRESSIVA":"COUNTDOWN",
        "Não perca tempo e aproveite esse primeiro lote com inscrição gratuita no The Customer Summit.":"Don't waste time and enjoy this first batch with free registration at The Customer Summit."

    }
}